brain.py
brain_cli-1.0.5.dist-info/METADATA
brain_cli-1.0.5.dist-info/WHEEL
brain_cli-1.0.5.dist-info/entry_points.txt
brain_cli-1.0.5.dist-info/top_level.txt
brain_cli-1.0.5.dist-info/RECORD
