Metadata-Version: 2.4
Name: brain-cli
Version: 1.0.5
Requires-Dist: typer>=0.9.0
Requires-Dist: rich>=13.0.0
Requires-Dist: groq>=0.4.0
Requires-Dist: pyperclip>=1.8.0
Requires-Dist: typing-extensions>=4.0.0
Dynamic: requires-dist
